sunnybeamtool/__init__.py
sunnybeamtool/const.py
sunnybeamtool/sunnybeamtool.py
sunnybeamtool-1.0.3.dist-info/LICENSE
sunnybeamtool-1.0.3.dist-info/METADATA
sunnybeamtool-1.0.3.dist-info/WHEEL
sunnybeamtool-1.0.3.dist-info/top_level.txt
sunnybeamtool-1.0.3.dist-info/RECORD
