Metadata-Version: 2.1
Name: sunnybeamtool
Version: 1.0.3
Summary: SMA Sunny Beam Tool
Author-email: Philipp Danner <philipp@danner-web.de>
License: GNU LESSER GENERAL PUBLIC LICENSE
Requires-Python: >=3.10
License-File: LICENSE
Requires-Dist: crcmod ~=1.7
Requires-Dist: pyusb ~=1.2.1
Provides-Extra: dev
Requires-Dist: mypy ; extra == 'dev'
Requires-Dist: black ; extra == 'dev'
Requires-Dist: isort ; extra == 'dev'
